exponent/__init__.py
exponent/cli.py
exponent/core/config.py
exponent/core/remote_execution/client.py
exponent/core/remote_execution/types.py
exponent/tests/__init__.py
exponent/tests/conftest.py
exponent/tests/test_cli.py
exponent_publication-0.0.1a4.dist-info/METADATA
exponent_publication-0.0.1a4.dist-info/WHEEL
exponent_publication-0.0.1a4.dist-info/entry_points.txt
exponent_publication-0.0.1a4.dist-info/RECORD
