Metadata-Version: 2.1
Name: exponent-publication
Version: 0.0.1a4
Summary: Exponent is an AI Pair Programmer
Author: Sashank Thupukari
Author-email: sashank@exponent.run
Requires-Python: >=3.12,<4.0
Classifier: Programming Language :: Python :: 3
Classifier: Programming Language :: Python :: 3.12
Requires-Dist: click (>=8.1.7,<9.0.0)
Requires-Dist: httpx (>=0.27.0,<0.28.0)
Requires-Dist: pydantic-settings (>=2.2.1,<3.0.0)
Requires-Dist: pydantic[dotenv,email] (>=2.6.4,<3.0.0)
Requires-Dist: pytest-env (>=1.1.3,<2.0.0)
